topsis/102203584.py
topsis/__init__.py
Topsis_Trish_Rustagi_102203584-0.1.0.dist-info/LICENSE
Topsis_Trish_Rustagi_102203584-0.1.0.dist-info/METADATA
Topsis_Trish_Rustagi_102203584-0.1.0.dist-info/WHEEL
Topsis_Trish_Rustagi_102203584-0.1.0.dist-info/top_level.txt
Topsis_Trish_Rustagi_102203584-0.1.0.dist-info/RECORD
