Metadata-Version: 2.2
Name: Topsis-Trish_Rustagi-102203584
Version: 0.1.0
Summary: A Python package for implementing the TOPSIS method.
Home-page: https://github.com/trish-r/Topsis-Trish_Rustagi-102203584.git
Author: Trish Rustagi
Author-email: trishrustagi@gmail.com
Classifier: Programming Language :: Python :: 3
Classifier: License :: OSI Approved :: MIT License
Classifier: Operating System :: OS Independent
Requires-Python: >=3.6
License-File: LICENSE
Requires-Dist: numpy
Requires-Dist: pandas
Dynamic: author
Dynamic: author-email
Dynamic: classifier
Dynamic: description
Dynamic: description-content-type
Dynamic: home-page
Dynamic: requires-dist
Dynamic: requires-python
Dynamic: summary
